pybind11_example.cp38-win_amd64.pyd
pybind11_example-0.3.dist-info/METADATA
pybind11_example-0.3.dist-info/WHEEL
pybind11_example-0.3.dist-info/top_level.txt
pybind11_example-0.3.dist-info/RECORD
